keruk/__init__.py
keruk-0.2.0.dist-info/LICENSE
keruk-0.2.0.dist-info/WHEEL
keruk-0.2.0.dist-info/METADATA
keruk-0.2.0.dist-info/RECORD
